[{"name":"vc.builder.install","duration":564887,"timestamp":616839405763,"id":"0222fb22-765b-442e-a7d7-173714ef02c8","parentId":"7ceed269-be4f-4bc6-bee7-75894aef404f","tags":{"cliType":"pnpm","lockfileVersion":"9","detectedPackageManager":"pnpm@9.x"},"startTime":1774185381418},{"name":"vc.builder.build","duration":16415071,"timestamp":616839971732,"id":"8e97aea9-0925-42db-93a8-708544a5a4c4","parentId":"7ceed269-be4f-4bc6-bee7-75894aef404f","tags":{"buildScriptName":"build"},"startTime":1774185381984},{"name":"vc.builder","duration":17472346,"timestamp":616839370385,"id":"7ceed269-be4f-4bc6-bee7-75894aef404f","parentId":"c3e7c289-5774-4508-8f81-5210bfcf6f2f","tags":{"builder.name":"@vercel/next","builder.version":"4.16.2","builder.dynamicallyInstalled":"false","install":"true","build":"true"},"startTime":1774185381383},{"name":"vc.builder.diagnostics","duration":658,"timestamp":616856842817,"id":"7dc72efd-37e9-477d-8ace-613e33973ea8","parentId":"7ceed269-be4f-4bc6-bee7-75894aef404f","tags":{},"startTime":1774185398855},{"name":"vc.builder.writeBuildResult","duration":25943,"timestamp":616856843549,"id":"ee780e38-9eec-4864-84ae-4754a56f93ab","parentId":"7ceed269-be4f-4bc6-bee7-75894aef404f","tags":{"buildOutputLength":"1"},"startTime":1774185398856},{"name":"vc.doBuild","duration":17584606,"timestamp":616839294440,"id":"c3e7c289-5774-4508-8f81-5210bfcf6f2f","parentId":"08aa3ee9-6721-4862-bae3-8daf38d189b3","tags":{},"startTime":1774185381307},{"name":"vc","duration":17607282,"timestamp":616839271779,"id":"08aa3ee9-6721-4862-bae3-8daf38d189b3","tags":{},"startTime":1774185381284}]